structeval/__init__.py
structeval/cli.py
structeval/exceptions.py
structeval/struct_evaluator.py
structeval/array_helpers/__init__.py
structeval/array_helpers/flattening.py
structeval/array_helpers/pairing.py
structeval/compare/__init__.py
structeval/compare/types.py
structeval/compare/methods/__init__.py
structeval/compare/methods/helpers/cosine.py
structeval/compare/methods/helpers/embedding.py
structeval/compare/methods/helpers/jaccard.py
structeval/compare/methods/scalar/__init__.py
structeval/compare/methods/scalar/binary_typed_evalutor.py
structeval/compare/methods/scalar/composed_type_evaluator.py
structeval/compare/methods/scalar/threshold_type_evaluator.py
structeval/compare/methods/scalar/typed_evaluator.py
structeval/compare/methods/vector/__init__.py
structeval/compare/methods/vector/composed_typed_evaluator.py
structeval/compare/methods/vector/cosine_typed_evaluator.py
structeval/compare/methods/vector/jaccard_typed_evaluator.py
structeval/compare/methods/vector/typed_evaluator.py
structeval/models/compare_result.py
structeval/models/eval_config.py
structeval/models/evaluators.py
structeval/models/field_overrides.py
structeval/models/json_schema.py
structeval/models/sum_metrics.py
structeval/models/value_node.py
structeval/reporting/html.py
structeval/reporting/text.py
structeval-0.1.1.dist-info/METADATA
structeval-0.1.1.dist-info/WHEEL
structeval-0.1.1.dist-info/entry_points.txt
structeval-0.1.1.dist-info/licenses/LICENSE
structeval-0.1.1.dist-info/RECORD
