Metadata-Version: 2.4
Name: structeval
Version: 0.1.1
Summary: A lightweight library for doing smart, semantically aware json diffs
Project-URL: Homepage, https://github.com/jhiker/structeval
Project-URL: Repository, https://github.com/jhiker/structeval
Project-URL: Issues, https://github.com/jhiker/structeval/issues
Author-email: Jonathan Leslie <jonathanleslie73@gmail.com>
License: MIT License
License-File: LICENSE
Keywords: diff,embeddings,evaluation,json
Classifier: Development Status :: 3 - Alpha
Classifier: License :: OSI Approved :: MIT License
Classifier: Programming Language :: Python
Classifier: Programming Language :: Python :: 3
Classifier: Programming Language :: Python :: 3 :: Only
Classifier: Programming Language :: Python :: 3.9
Classifier: Programming Language :: Python :: 3.10
Classifier: Programming Language :: Python :: 3.11
Classifier: Programming Language :: Python :: 3.12
Classifier: Typing :: Typed
Requires-Python: >=3.12
Requires-Dist: numpy>=1.23
Requires-Dist: pydantic>=2.12.3
Requires-Dist: scipy>=1.9
Requires-Dist: sentence-transformers>=5.1.2
Provides-Extra: dev
Requires-Dist: hypothesis>=6.14; extra == 'dev'
Requires-Dist: mypy>=1.8; extra == 'dev'
Requires-Dist: pre-commit>=3.6; extra == 'dev'
Requires-Dist: pytest-cov>=4; extra == 'dev'
Requires-Dist: pytest>=7; extra == 'dev'
Requires-Dist: ruff>=0.4; extra == 'dev'
Provides-Extra: docs
Requires-Dist: mkdocs-material>=9; extra == 'docs'
Requires-Dist: mkdocs>=1.5; extra == 'docs'
Requires-Dist: mkdocstrings[python]>=0.24; extra == 'docs'
